[{"id":"17860156388053110","text":"Godochi","created_at":1595341849,"did_report_as_spam":false,"owner":{"id":"2463383396","is_verified":false,"profile_pic_url":"https://scontent-ort2-1.cdninstagram.com/v/t51.2885-19/s150x150/12424832_1516056602056233_1888758906_a.jpg?_nc_ht=scontent-ort2-1.cdninstagram.com&_nc_ohc=q380IOkJBRIAX-JDdHW&oh=23fe13aa95e0bfa01c78b79db94eabf7&oe=5F422DC1","username":"taygaizer"},"likes":0,"comments":1},{"id":"17934917572387048","text":"Gidochi","created_at":1595341920,"did_report_as_spam":false,"owner":{"id":"2463383396","is_verified":false,"profile_pic_url":"https://scontent-ort2-1.cdninstagram.com/v/t51.2885-19/s150x150/12424832_1516056602056233_1888758906_a.jpg?_nc_ht=scontent-ort2-1.cdninstagram.com&_nc_ohc=q380IOkJBRIAX-JDdHW&oh=23fe13aa95e0bfa01c78b79db94eabf7&oe=5F422DC1","username":"taygaizer"},"likes":0,"comments":0}]