[{"id":"18152911336015709","text":"GIDOCHI","created_at":1595627464,"did_report_as_spam":false,"owner":{"id":"7468557098","is_verified":false,"profile_pic_url":"https://scontent-ort2-1.cdninstagram.com/v/t51.2885-19/s150x150/62575851_480915255810600_5071732025770115072_n.jpg?_nc_ht=scontent-ort2-1.cdninstagram.com&_nc_ohc=wwz_CZJEW1sAX_g6vpA&oh=1f7dc42010d4bcc43a425cf575cd0335&oe=5F45ABE0","username":"biggkwamz"},"likes":0,"comments":0},{"id":"17875924885773967","text":"Gidochi","created_at":1595627472,"did_report_as_spam":false,"owner":{"id":"7468557098","is_verified":false,"profile_pic_url":"https://scontent-ort2-1.cdninstagram.com/v/t51.2885-19/s150x150/62575851_480915255810600_5071732025770115072_n.jpg?_nc_ht=scontent-ort2-1.cdninstagram.com&_nc_ohc=wwz_CZJEW1sAX_g6vpA&oh=1f7dc42010d4bcc43a425cf575cd0335&oe=5F45ABE0","username":"biggkwamz"},"likes":0,"comments":0},{"id":"17848106990245952","text":"GIDOCHI","created_at":1595627478,"did_report_as_spam":false,"owner":{"id":"7468557098","is_verified":false,"profile_pic_url":"https://scontent-ort2-1.cdninstagram.com/v/t51.2885-19/s150x150/62575851_480915255810600_5071732025770115072_n.jpg?_nc_ht=scontent-ort2-1.cdninstagram.com&_nc_ohc=wwz_CZJEW1sAX_g6vpA&oh=1f7dc42010d4bcc43a425cf575cd0335&oe=5F45ABE0","username":"biggkwamz"},"likes":0,"comments":0},{"id":"17884007233658459","text":"Gidochi","created_at":1595627482,"did_report_as_spam":false,"owner":{"id":"7468557098","is_verified":false,"profile_pic_url":"https://scontent-ort2-1.cdninstagram.com/v/t51.2885-19/s150x150/62575851_480915255810600_5071732025770115072_n.jpg?_nc_ht=scontent-ort2-1.cdninstagram.com&_nc_ohc=wwz_CZJEW1sAX_g6vpA&oh=1f7dc42010d4bcc43a425cf575cd0335&oe=5F45ABE0","username":"biggkwamz"},"likes":0,"comments":0},{"id":"17869904182849792","text":"Spookythemaniac","created_at":1595627486,"did_report_as_spam":false,"owner":{"id":"5561880328","is_verified":false,"profile_pic_url":"https://scontent-ort2-1.cdninstagram.com/v/t51.2885-19/s150x150/79805889_1384296701779345_2358308684729155584_n.jpg?_nc_ht=scontent-ort2-1.cdninstagram.com&_nc_ohc=oZ9xawOg4ikAX_-lZ0A&oh=9666f53d774b11d401e47081f6c1bc71&oe=5F43184C","username":"quansah.kingsley"},"likes":0,"comments":0},{"id":"17889926824601748","text":"GIDOCHI","created_at":1595627489,"did_report_as_spam":false,"owner":{"id":"7468557098","is_verified":false,"profile_pic_url":"https://scontent-ort2-1.cdninstagram.com/v/t51.2885-19/s150x150/62575851_480915255810600_5071732025770115072_n.jpg?_nc_ht=scontent-ort2-1.cdninstagram.com&_nc_ohc=wwz_CZJEW1sAX_g6vpA&oh=1f7dc42010d4bcc43a425cf575cd0335&oe=5F45ABE0","username":"biggkwamz"},"likes":0,"comments":0},{"id":"18116856079190335","text":"Gidochi","created_at":1595627494,"did_report_as_spam":false,"owner":{"id":"7468557098","is_verified":false,"profile_pic_url":"https://scontent-ort2-1.cdninstagram.com/v/t51.2885-19/s150x150/62575851_480915255810600_5071732025770115072_n.jpg?_nc_ht=scontent-ort2-1.cdninstagram.com&_nc_ohc=wwz_CZJEW1sAX_g6vpA&oh=1f7dc42010d4bcc43a425cf575cd0335&oe=5F45ABE0","username":"biggkwamz"},"likes":0,"comments":0},{"id":"18044986741251403","text":"GIDOCHI","created_at":1595627499,"did_report_as_spam":false,"owner":{"id":"7468557098","is_verified":false,"profile_pic_url":"https://scontent-ort2-1.cdninstagram.com/v/t51.2885-19/s150x150/62575851_480915255810600_5071732025770115072_n.jpg?_nc_ht=scontent-ort2-1.cdninstagram.com&_nc_ohc=wwz_CZJEW1sAX_g6vpA&oh=1f7dc42010d4bcc43a425cf575cd0335&oe=5F45ABE0","username":"biggkwamz"},"likes":0,"comments":0},{"id":"17866830304925061","text":"Gidochi","created_at":1595627502,"did_report_as_spam":false,"owner":{"id":"7468557098","is_verified":false,"profile_pic_url":"https://scontent-ort2-1.cdninstagram.com/v/t51.2885-19/s150x150/62575851_480915255810600_5071732025770115072_n.jpg?_nc_ht=scontent-ort2-1.cdninstagram.com&_nc_ohc=wwz_CZJEW1sAX_g6vpA&oh=1f7dc42010d4bcc43a425cf575cd0335&oe=5F45ABE0","username":"biggkwamz"},"likes":0,"comments":0},{"id":"17923348189415935","text":"GIDOCHI","created_at":1595627506,"did_report_as_spam":false,"owner":{"id":"7468557098","is_verified":false,"profile_pic_url":"https://scontent-ort2-1.cdninstagram.com/v/t51.2885-19/s150x150/62575851_480915255810600_5071732025770115072_n.jpg?_nc_ht=scontent-ort2-1.cdninstagram.com&_nc_ohc=wwz_CZJEW1sAX_g6vpA&oh=1f7dc42010d4bcc43a425cf575cd0335&oe=5F45ABE0","username":"biggkwamz"},"likes":0,"comments":0},{"id":"18110532718147909","text":"Gidochi","created_at":1595627508,"did_report_as_spam":false,"owner":{"id":"7468557098","is_verified":false,"profile_pic_url":"https://scontent-ort2-1.cdninstagram.com/v/t51.2885-19/s150x150/62575851_480915255810600_5071732025770115072_n.jpg?_nc_ht=scontent-ort2-1.cdninstagram.com&_nc_ohc=wwz_CZJEW1sAX_g6vpA&oh=1f7dc42010d4bcc43a425cf575cd0335&oe=5F45ABE0","username":"biggkwamz"},"likes":0,"comments":0},{"id":"17873509321791819","text":"GIDOCHI","created_at":1595627512,"did_report_as_spam":false,"owner":{"id":"7468557098","is_verified":false,"profile_pic_url":"https://scontent-ort2-1.cdninstagram.com/v/t51.2885-19/s150x150/62575851_480915255810600_5071732025770115072_n.jpg?_nc_ht=scontent-ort2-1.cdninstagram.com&_nc_ohc=wwz_CZJEW1sAX_g6vpA&oh=1f7dc42010d4bcc43a425cf575cd0335&oe=5F45ABE0","username":"biggkwamz"},"likes":0,"comments":0},{"id":"18065586475225445","text":"Gidochi","created_at":1595627513,"did_report_as_spam":false,"owner":{"id":"7468557098","is_verified":false,"profile_pic_url":"https://scontent-ort2-1.cdninstagram.com/v/t51.2885-19/s150x150/62575851_480915255810600_5071732025770115072_n.jpg?_nc_ht=scontent-ort2-1.cdninstagram.com&_nc_ohc=wwz_CZJEW1sAX_g6vpA&oh=1f7dc42010d4bcc43a425cf575cd0335&oe=5F45ABE0","username":"biggkwamz"},"likes":0,"comments":0}]