[{"id":"17935745884384257","text":"@Spookythemaniac","created_at":1595510464,"did_report_as_spam":false,"owner":{"id":"5984191003","is_verified":false,"profile_pic_url":"https://scontent-ort2-1.cdninstagram.com/v/t51.2885-19/s150x150/53740004_2333600480253392_692097957859688448_n.jpg?_nc_ht=scontent-ort2-1.cdninstagram.com&_nc_ohc=U2kB898iE64AX8bses3&oh=2880a80098fbd400297da9d3c01fe4c8&oe=5F420763","username":"yemohbigsam"},"likes":1,"comments":0},{"id":"17848778105227074","text":"@spookythemaniac","created_at":1595510561,"did_report_as_spam":false,"owner":{"id":"14421024239","is_verified":false,"profile_pic_url":"https://scontent-ort2-1.cdninstagram.com/v/t51.2885-19/s150x150/82817337_819423881875279_2535847372726992896_n.jpg?_nc_ht=scontent-ort2-1.cdninstagram.com&_nc_ohc=UFONpGcnACYAX8-bPiz&oh=db271f84bc465beee5d2d27848ede66f&oe=5F4203C4","username":"nuella_kelsey"},"likes":1,"comments":0},{"id":"17935694269378294","text":"@spookythemaniac","created_at":1595510568,"did_report_as_spam":false,"owner":{"id":"14421024239","is_verified":false,"profile_pic_url":"https://scontent-ort2-1.cdninstagram.com/v/t51.2885-19/s150x150/82817337_819423881875279_2535847372726992896_n.jpg?_nc_ht=scontent-ort2-1.cdninstagram.com&_nc_ohc=UFONpGcnACYAX8-bPiz&oh=db271f84bc465beee5d2d27848ede66f&oe=5F4203C4","username":"nuella_kelsey"},"likes":1,"comments":0},{"id":"17881918609717640","text":"@spookythemaniac","created_at":1595510572,"did_report_as_spam":false,"owner":{"id":"14421024239","is_verified":false,"profile_pic_url":"https://scontent-ort2-1.cdninstagram.com/v/t51.2885-19/s150x150/82817337_819423881875279_2535847372726992896_n.jpg?_nc_ht=scontent-ort2-1.cdninstagram.com&_nc_ohc=UFONpGcnACYAX8-bPiz&oh=db271f84bc465beee5d2d27848ede66f&oe=5F4203C4","username":"nuella_kelsey"},"likes":1,"comments":0},{"id":"18141104290076234","text":"@spookythemaniac","created_at":1595510577,"did_report_as_spam":false,"owner":{"id":"14421024239","is_verified":false,"profile_pic_url":"https://scontent-ort2-1.cdninstagram.com/v/t51.2885-19/s150x150/82817337_819423881875279_2535847372726992896_n.jpg?_nc_ht=scontent-ort2-1.cdninstagram.com&_nc_ohc=UFONpGcnACYAX8-bPiz&oh=db271f84bc465beee5d2d27848ede66f&oe=5F4203C4","username":"nuella_kelsey"},"likes":1,"comments":0},{"id":"18018579454285018","text":"@spookythemaniac","created_at":1595510582,"did_report_as_spam":false,"owner":{"id":"14421024239","is_verified":false,"profile_pic_url":"https://scontent-ort2-1.cdninstagram.com/v/t51.2885-19/s150x150/82817337_819423881875279_2535847372726992896_n.jpg?_nc_ht=scontent-ort2-1.cdninstagram.com&_nc_ohc=UFONpGcnACYAX8-bPiz&oh=db271f84bc465beee5d2d27848ede66f&oe=5F4203C4","username":"nuella_kelsey"},"likes":1,"comments":0},{"id":"18124356169115482","text":"@spookythemaniac","created_at":1595510583,"did_report_as_spam":false,"owner":{"id":"14421024239","is_verified":false,"profile_pic_url":"https://scontent-ort2-1.cdninstagram.com/v/t51.2885-19/s150x150/82817337_819423881875279_2535847372726992896_n.jpg?_nc_ht=scontent-ort2-1.cdninstagram.com&_nc_ohc=UFONpGcnACYAX8-bPiz&oh=db271f84bc465beee5d2d27848ede66f&oe=5F4203C4","username":"nuella_kelsey"},"likes":1,"comments":0},{"id":"17860107305018723","text":"@spookythemaniac","created_at":1595510588,"did_report_as_spam":false,"owner":{"id":"14421024239","is_verified":false,"profile_pic_url":"https://scontent-ort2-1.cdninstagram.com/v/t51.2885-19/s150x150/82817337_819423881875279_2535847372726992896_n.jpg?_nc_ht=scontent-ort2-1.cdninstagram.com&_nc_ohc=UFONpGcnACYAX8-bPiz&oh=db271f84bc465beee5d2d27848ede66f&oe=5F4203C4","username":"nuella_kelsey"},"likes":1,"comments":0},{"id":"18116881411185909","text":"@spookythemaniac","created_at":1595510602,"did_report_as_spam":false,"owner":{"id":"14421024239","is_verified":false,"profile_pic_url":"https://scontent-ort2-1.cdninstagram.com/v/t51.2885-19/s150x150/82817337_819423881875279_2535847372726992896_n.jpg?_nc_ht=scontent-ort2-1.cdninstagram.com&_nc_ohc=UFONpGcnACYAX8-bPiz&oh=db271f84bc465beee5d2d27848ede66f&oe=5F4203C4","username":"nuella_kelsey"},"likes":1,"comments":0},{"id":"17880781261681546","text":"@spookythemaniac","created_at":1595510614,"did_report_as_spam":false,"owner":{"id":"14421024239","is_verified":false,"profile_pic_url":"https://scontent-ort2-1.cdninstagram.com/v/t51.2885-19/s150x150/82817337_819423881875279_2535847372726992896_n.jpg?_nc_ht=scontent-ort2-1.cdninstagram.com&_nc_ohc=UFONpGcnACYAX8-bPiz&oh=db271f84bc465beee5d2d27848ede66f&oe=5F4203C4","username":"nuella_kelsey"},"likes":1,"comments":0}]