[{"id":"18029543761279645","text":"Nessa","created_at":1595721241,"did_report_as_spam":false,"owner":{"id":"5356631375","is_verified":false,"profile_pic_url":"https://scontent-ort2-1.cdninstagram.com/v/t51.2885-19/s150x150/106912035_628626791090649_4675324471155298879_n.jpg?_nc_ht=scontent-ort2-1.cdninstagram.com&_nc_ohc=DSzQpLh7Gz4AX_T6iBm&oh=9fcba9d697412b69048bd2d685507391&oe=5F47172A","username":"sikiaeli"},"likes":0,"comments":0},{"id":"17865219745935806","text":"Nessa","created_at":1595721242,"did_report_as_spam":false,"owner":{"id":"5342189681","is_verified":false,"profile_pic_url":"https://scontent-ort2-1.cdninstagram.com/v/t51.2885-19/s150x150/69973370_897964113914583_7977691479311122432_n.jpg?_nc_ht=scontent-ort2-1.cdninstagram.com&_nc_ohc=ozwXBlMq0QUAX83xjx0&oh=c6a3e7207eb788c69024991f3802e3b6&oe=5F45562D","username":"thehuefactory.co"},"likes":0,"comments":0},{"id":"17865389575902608","text":"Nessa","created_at":1595721244,"did_report_as_spam":false,"owner":{"id":"5356631375","is_verified":false,"profile_pic_url":"https://scontent-ort2-1.cdninstagram.com/v/t51.2885-19/s150x150/106912035_628626791090649_4675324471155298879_n.jpg?_nc_ht=scontent-ort2-1.cdninstagram.com&_nc_ohc=DSzQpLh7Gz4AX_T6iBm&oh=9fcba9d697412b69048bd2d685507391&oe=5F47172A","username":"sikiaeli"},"likes":0,"comments":0},{"id":"17907033064469458","text":"Nessa","created_at":1595721245,"did_report_as_spam":false,"owner":{"id":"5342189681","is_verified":false,"profile_pic_url":"https://scontent-ort2-1.cdninstagram.com/v/t51.2885-19/s150x150/69973370_897964113914583_7977691479311122432_n.jpg?_nc_ht=scontent-ort2-1.cdninstagram.com&_nc_ohc=ozwXBlMq0QUAX83xjx0&oh=c6a3e7207eb788c69024991f3802e3b6&oe=5F45562D","username":"thehuefactory.co"},"likes":0,"comments":0},{"id":"17850907343170531","text":"Nessa","created_at":1595721248,"did_report_as_spam":false,"owner":{"id":"5356631375","is_verified":false,"profile_pic_url":"https://scontent-ort2-1.cdninstagram.com/v/t51.2885-19/s150x150/106912035_628626791090649_4675324471155298879_n.jpg?_nc_ht=scontent-ort2-1.cdninstagram.com&_nc_ohc=DSzQpLh7Gz4AX_T6iBm&oh=9fcba9d697412b69048bd2d685507391&oe=5F47172A","username":"sikiaeli"},"likes":0,"comments":0},{"id":"17873218924812509","text":"Nessa","created_at":1595721252,"did_report_as_spam":false,"owner":{"id":"5356631375","is_verified":false,"profile_pic_url":"https://scontent-ort2-1.cdninstagram.com/v/t51.2885-19/s150x150/106912035_628626791090649_4675324471155298879_n.jpg?_nc_ht=scontent-ort2-1.cdninstagram.com&_nc_ohc=DSzQpLh7Gz4AX_T6iBm&oh=9fcba9d697412b69048bd2d685507391&oe=5F47172A","username":"sikiaeli"},"likes":0,"comments":0},{"id":"18111342253179286","text":"NESSA","created_at":1595721252,"did_report_as_spam":false,"owner":{"id":"692683772","is_verified":false,"profile_pic_url":"https://scontent-ort2-1.cdninstagram.com/v/t51.2885-19/s150x150/42512048_1995410210510591_3965101176168382464_n.jpg?_nc_ht=scontent-ort2-1.cdninstagram.com&_nc_ohc=XyTISM7gbeAAX_1J0D7&oh=88bdcb8c0eb78c89b42e6f90d4a280a6&oe=5F475203","username":"kingkapture"},"likes":0,"comments":0},{"id":"17862996241995235","text":"Nessa","created_at":1595721254,"did_report_as_spam":false,"owner":{"id":"5342189681","is_verified":false,"profile_pic_url":"https://scontent-ort2-1.cdninstagram.com/v/t51.2885-19/s150x150/69973370_897964113914583_7977691479311122432_n.jpg?_nc_ht=scontent-ort2-1.cdninstagram.com&_nc_ohc=ozwXBlMq0QUAX83xjx0&oh=c6a3e7207eb788c69024991f3802e3b6&oe=5F45562D","username":"thehuefactory.co"},"likes":0,"comments":0},{"id":"17855622539089452","text":"Nessa","created_at":1595721255,"did_report_as_spam":false,"owner":{"id":"5356631375","is_verified":false,"profile_pic_url":"https://scontent-ort2-1.cdninstagram.com/v/t51.2885-19/s150x150/106912035_628626791090649_4675324471155298879_n.jpg?_nc_ht=scontent-ort2-1.cdninstagram.com&_nc_ohc=DSzQpLh7Gz4AX_T6iBm&oh=9fcba9d697412b69048bd2d685507391&oe=5F47172A","username":"sikiaeli"},"likes":0,"comments":0},{"id":"17865407008928330","text":"NESSA","created_at":1595721256,"did_report_as_spam":false,"owner":{"id":"692683772","is_verified":false,"profile_pic_url":"https://scontent-ort2-1.cdninstagram.com/v/t51.2885-19/s150x150/42512048_1995410210510591_3965101176168382464_n.jpg?_nc_ht=scontent-ort2-1.cdninstagram.com&_nc_ohc=XyTISM7gbeAAX_1J0D7&oh=88bdcb8c0eb78c89b42e6f90d4a280a6&oe=5F475203","username":"kingkapture"},"likes":0,"comments":0},{"id":"17850366959178662","text":"Nessa","created_at":1595721258,"did_report_as_spam":false,"owner":{"id":"5356631375","is_verified":false,"profile_pic_url":"https://scontent-ort2-1.cdninstagram.com/v/t51.2885-19/s150x150/106912035_628626791090649_4675324471155298879_n.jpg?_nc_ht=scontent-ort2-1.cdninstagram.com&_nc_ohc=DSzQpLh7Gz4AX_T6iBm&oh=9fcba9d697412b69048bd2d685507391&oe=5F47172A","username":"sikiaeli"},"likes":0,"comments":0},{"id":"17848596788197862","text":"Nessa","created_at":1595721261,"did_report_as_spam":false,"owner":{"id":"5342189681","is_verified":false,"profile_pic_url":"https://scontent-ort2-1.cdninstagram.com/v/t51.2885-19/s150x150/69973370_897964113914583_7977691479311122432_n.jpg?_nc_ht=scontent-ort2-1.cdninstagram.com&_nc_ohc=ozwXBlMq0QUAX83xjx0&oh=c6a3e7207eb788c69024991f3802e3b6&oe=5F45562D","username":"thehuefactory.co"},"likes":0,"comments":0},{"id":"17887262539620084","text":"Nessa","created_at":1595721261,"did_report_as_spam":false,"owner":{"id":"5356631375","is_verified":false,"profile_pic_url":"https://scontent-ort2-1.cdninstagram.com/v/t51.2885-19/s150x150/106912035_628626791090649_4675324471155298879_n.jpg?_nc_ht=scontent-ort2-1.cdninstagram.com&_nc_ohc=DSzQpLh7Gz4AX_T6iBm&oh=9fcba9d697412b69048bd2d685507391&oe=5F47172A","username":"sikiaeli"},"likes":0,"comments":0},{"id":"17888742205608923","text":"Nessa","created_at":1595721262,"did_report_as_spam":false,"owner":{"id":"5342189681","is_verified":false,"profile_pic_url":"https://scontent-ort2-1.cdninstagram.com/v/t51.2885-19/s150x150/69973370_897964113914583_7977691479311122432_n.jpg?_nc_ht=scontent-ort2-1.cdninstagram.com&_nc_ohc=ozwXBlMq0QUAX83xjx0&oh=c6a3e7207eb788c69024991f3802e3b6&oe=5F45562D","username":"thehuefactory.co"},"likes":0,"comments":0},{"id":"17876296018745607","text":"NESSA","created_at":1595721263,"did_report_as_spam":false,"owner":{"id":"692683772","is_verified":false,"profile_pic_url":"https://scontent-ort2-1.cdninstagram.com/v/t51.2885-19/s150x150/42512048_1995410210510591_3965101176168382464_n.jpg?_nc_ht=scontent-ort2-1.cdninstagram.com&_nc_ohc=XyTISM7gbeAAX_1J0D7&oh=88bdcb8c0eb78c89b42e6f90d4a280a6&oe=5F475203","username":"kingkapture"},"likes":0,"comments":0},{"id":"17897072023536634","text":"Nessa","created_at":1595721263,"did_report_as_spam":false,"owner":{"id":"5342189681","is_verified":false,"profile_pic_url":"https://scontent-ort2-1.cdninstagram.com/v/t51.2885-19/s150x150/69973370_897964113914583_7977691479311122432_n.jpg?_nc_ht=scontent-ort2-1.cdninstagram.com&_nc_ohc=ozwXBlMq0QUAX83xjx0&oh=c6a3e7207eb788c69024991f3802e3b6&oe=5F45562D","username":"thehuefactory.co"},"likes":0,"comments":0},{"id":"17885236507629790","text":"Nessa","created_at":1595721265,"did_report_as_spam":false,"owner":{"id":"5342189681","is_verified":false,"profile_pic_url":"https://scontent-ort2-1.cdninstagram.com/v/t51.2885-19/s150x150/69973370_897964113914583_7977691479311122432_n.jpg?_nc_ht=scontent-ort2-1.cdninstagram.com&_nc_ohc=ozwXBlMq0QUAX83xjx0&oh=c6a3e7207eb788c69024991f3802e3b6&oe=5F45562D","username":"thehuefactory.co"},"likes":0,"comments":0},{"id":"17867041636916242","text":"Nessa","created_at":1595721269,"did_report_as_spam":false,"owner":{"id":"5342189681","is_verified":false,"profile_pic_url":"https://scontent-ort2-1.cdninstagram.com/v/t51.2885-19/s150x150/69973370_897964113914583_7977691479311122432_n.jpg?_nc_ht=scontent-ort2-1.cdninstagram.com&_nc_ohc=ozwXBlMq0QUAX83xjx0&oh=c6a3e7207eb788c69024991f3802e3b6&oe=5F45562D","username":"thehuefactory.co"},"likes":0,"comments":0},{"id":"18156881434057416","text":"Nessa","created_at":1595721270,"did_report_as_spam":false,"owner":{"id":"5342189681","is_verified":false,"profile_pic_url":"https://scontent-ort2-1.cdninstagram.com/v/t51.2885-19/s150x150/69973370_897964113914583_7977691479311122432_n.jpg?_nc_ht=scontent-ort2-1.cdninstagram.com&_nc_ohc=ozwXBlMq0QUAX83xjx0&oh=c6a3e7207eb788c69024991f3802e3b6&oe=5F45562D","username":"thehuefactory.co"},"likes":0,"comments":0},{"id":"17911489087461253","text":"Nessa","created_at":1595721272,"did_report_as_spam":false,"owner":{"id":"5342189681","is_verified":false,"profile_pic_url":"https://scontent-ort2-1.cdninstagram.com/v/t51.2885-19/s150x150/69973370_897964113914583_7977691479311122432_n.jpg?_nc_ht=scontent-ort2-1.cdninstagram.com&_nc_ohc=ozwXBlMq0QUAX83xjx0&oh=c6a3e7207eb788c69024991f3802e3b6&oe=5F45562D","username":"thehuefactory.co"},"likes":0,"comments":0},{"id":"17876038432746837","text":"NESSA","created_at":1595721292,"did_report_as_spam":false,"owner":{"id":"692683772","is_verified":false,"profile_pic_url":"https://scontent-ort2-1.cdninstagram.com/v/t51.2885-19/s150x150/42512048_1995410210510591_3965101176168382464_n.jpg?_nc_ht=scontent-ort2-1.cdninstagram.com&_nc_ohc=XyTISM7gbeAAX_1J0D7&oh=88bdcb8c0eb78c89b42e6f90d4a280a6&oe=5F475203","username":"kingkapture"},"likes":0,"comments":0},{"id":"18112760056080328","text":"Nessa","created_at":1595721292,"did_report_as_spam":false,"owner":{"id":"388277629","is_verified":false,"profile_pic_url":"https://scontent-ort2-1.cdninstagram.com/v/t51.2885-19/s150x150/96375565_2951329298247956_9077933182807965696_n.jpg?_nc_ht=scontent-ort2-1.cdninstagram.com&_nc_ohc=G4b2lT5w00AAX_6U0O_&oh=7cc69fc4bf7a64236b8e2bfd56402093&oe=5F483953","username":"life.of.gelo"},"likes":0,"comments":0},{"id":"18063573355228748","text":"NESSA","created_at":1595721295,"did_report_as_spam":false,"owner":{"id":"692683772","is_verified":false,"profile_pic_url":"https://scontent-ort2-1.cdninstagram.com/v/t51.2885-19/s150x150/42512048_1995410210510591_3965101176168382464_n.jpg?_nc_ht=scontent-ort2-1.cdninstagram.com&_nc_ohc=XyTISM7gbeAAX_1J0D7&oh=88bdcb8c0eb78c89b42e6f90d4a280a6&oe=5F475203","username":"kingkapture"},"likes":0,"comments":0},{"id":"17883675415648297","text":"Nessa","created_at":1595721297,"did_report_as_spam":false,"owner":{"id":"7032551032","is_verified":false,"profile_pic_url":"https://scontent-ort2-1.cdninstagram.com/v/t51.2885-19/s150x150/59795682_370272326917787_180190877547757568_n.jpg?_nc_ht=scontent-ort2-1.cdninstagram.com&_nc_ohc=QUIgxZN_kcQAX-6BvWD&oh=5053b4476b7ae1fcdac8a1b0b3534c83&oe=5F46C159","username":"nha_ddie"},"likes":0,"comments":0},{"id":"17863365643988070","text":"Nessa","created_at":1595721298,"did_report_as_spam":false,"owner":{"id":"388277629","is_verified":false,"profile_pic_url":"https://scontent-ort2-1.cdninstagram.com/v/t51.2885-19/s150x150/96375565_2951329298247956_9077933182807965696_n.jpg?_nc_ht=scontent-ort2-1.cdninstagram.com&_nc_ohc=G4b2lT5w00AAX_6U0O_&oh=7cc69fc4bf7a64236b8e2bfd56402093&oe=5F483953","username":"life.of.gelo"},"likes":0,"comments":0}]