[{"id":"17875418338796767","text":"Gidochi","created_at":1595501645,"did_report_as_spam":false,"owner":{"id":"3910718279","is_verified":false,"profile_pic_url":"https://scontent-ort2-1.cdninstagram.com/v/t51.2885-19/s150x150/107420253_316327142730772_6785603372380776169_n.jpg?_nc_ht=scontent-ort2-1.cdninstagram.com&_nc_ohc=LbSVvcZoDu4AX9PTINw&oh=22811f804e16df499c9af77643298ef5&oe=5F429BED","username":"amoakoa_"},"likes":0,"comments":0},{"id":"18005315362293760","text":"Gidochi","created_at":1595501657,"did_report_as_spam":false,"owner":{"id":"3910718279","is_verified":false,"profile_pic_url":"https://scontent-ort2-1.cdninstagram.com/v/t51.2885-19/s150x150/107420253_316327142730772_6785603372380776169_n.jpg?_nc_ht=scontent-ort2-1.cdninstagram.com&_nc_ohc=LbSVvcZoDu4AX9PTINw&oh=22811f804e16df499c9af77643298ef5&oe=5F429BED","username":"amoakoa_"},"likes":0,"comments":0},{"id":"18044840824254208","text":"Gidochi","created_at":1595501664,"did_report_as_spam":false,"owner":{"id":"3910718279","is_verified":false,"profile_pic_url":"https://scontent-ort2-1.cdninstagram.com/v/t51.2885-19/s150x150/107420253_316327142730772_6785603372380776169_n.jpg?_nc_ht=scontent-ort2-1.cdninstagram.com&_nc_ohc=LbSVvcZoDu4AX9PTINw&oh=22811f804e16df499c9af77643298ef5&oe=5F429BED","username":"amoakoa_"},"likes":0,"comments":0},{"id":"17881806613685149","text":"Gidochi","created_at":1595501667,"did_report_as_spam":false,"owner":{"id":"3910718279","is_verified":false,"profile_pic_url":"https://scontent-ort2-1.cdninstagram.com/v/t51.2885-19/s150x150/107420253_316327142730772_6785603372380776169_n.jpg?_nc_ht=scontent-ort2-1.cdninstagram.com&_nc_ohc=LbSVvcZoDu4AX9PTINw&oh=22811f804e16df499c9af77643298ef5&oe=5F429BED","username":"amoakoa_"},"likes":0,"comments":0},{"id":"18112677496083306","text":"Gidochi","created_at":1595501673,"did_report_as_spam":false,"owner":{"id":"3910718279","is_verified":false,"profile_pic_url":"https://scontent-ort2-1.cdninstagram.com/v/t51.2885-19/s150x150/107420253_316327142730772_6785603372380776169_n.jpg?_nc_ht=scontent-ort2-1.cdninstagram.com&_nc_ohc=LbSVvcZoDu4AX9PTINw&oh=22811f804e16df499c9af77643298ef5&oe=5F429BED","username":"amoakoa_"},"likes":0,"comments":0},{"id":"18110805739151044","text":"Gidochi","created_at":1595501679,"did_report_as_spam":false,"owner":{"id":"3910718279","is_verified":false,"profile_pic_url":"https://scontent-ort2-1.cdninstagram.com/v/t51.2885-19/s150x150/107420253_316327142730772_6785603372380776169_n.jpg?_nc_ht=scontent-ort2-1.cdninstagram.com&_nc_ohc=LbSVvcZoDu4AX9PTINw&oh=22811f804e16df499c9af77643298ef5&oe=5F429BED","username":"amoakoa_"},"likes":0,"comments":0},{"id":"18003610318294064","text":"Spooky","created_at":1595501786,"did_report_as_spam":false,"owner":{"id":"2652537964","is_verified":false,"profile_pic_url":"https://scontent-ort2-1.cdninstagram.com/v/t51.2885-19/s150x150/92024224_571394950144815_6785941292800016384_n.jpg?_nc_ht=scontent-ort2-1.cdninstagram.com&_nc_ohc=HGoGEHcRIWkAX_awCeB&oh=f7a064eaaa32db99daa9231823d46bb1&oe=5F414938","username":"nana_amakye_korankye"},"likes":0,"comments":0},{"id":"17852640599128919","text":"Spooky","created_at":1595501789,"did_report_as_spam":false,"owner":{"id":"2652537964","is_verified":false,"profile_pic_url":"https://scontent-ort2-1.cdninstagram.com/v/t51.2885-19/s150x150/92024224_571394950144815_6785941292800016384_n.jpg?_nc_ht=scontent-ort2-1.cdninstagram.com&_nc_ohc=HGoGEHcRIWkAX_awCeB&oh=f7a064eaaa32db99daa9231823d46bb1&oe=5F414938","username":"nana_amakye_korankye"},"likes":0,"comments":0},{"id":"17861559728011170","text":"Spooky","created_at":1595501793,"did_report_as_spam":false,"owner":{"id":"2652537964","is_verified":false,"profile_pic_url":"https://scontent-ort2-1.cdninstagram.com/v/t51.2885-19/s150x150/92024224_571394950144815_6785941292800016384_n.jpg?_nc_ht=scontent-ort2-1.cdninstagram.com&_nc_ohc=HGoGEHcRIWkAX_awCeB&oh=f7a064eaaa32db99daa9231823d46bb1&oe=5F414938","username":"nana_amakye_korankye"},"likes":0,"comments":0},{"id":"17889117046588114","text":"Spooky","created_at":1595501796,"did_report_as_spam":false,"owner":{"id":"2652537964","is_verified":false,"profile_pic_url":"https://scontent-ort2-1.cdninstagram.com/v/t51.2885-19/s150x150/92024224_571394950144815_6785941292800016384_n.jpg?_nc_ht=scontent-ort2-1.cdninstagram.com&_nc_ohc=HGoGEHcRIWkAX_awCeB&oh=f7a064eaaa32db99daa9231823d46bb1&oe=5F414938","username":"nana_amakye_korankye"},"likes":0,"comments":0},{"id":"18063580513232870","text":"Spooky","created_at":1595501801,"did_report_as_spam":false,"owner":{"id":"2652537964","is_verified":false,"profile_pic_url":"https://scontent-ort2-1.cdninstagram.com/v/t51.2885-19/s150x150/92024224_571394950144815_6785941292800016384_n.jpg?_nc_ht=scontent-ort2-1.cdninstagram.com&_nc_ohc=HGoGEHcRIWkAX_awCeB&oh=f7a064eaaa32db99daa9231823d46bb1&oe=5F414938","username":"nana_amakye_korankye"},"likes":0,"comments":0},{"id":"18154449538020034","text":"Spooky","created_at":1595501804,"did_report_as_spam":false,"owner":{"id":"2652537964","is_verified":false,"profile_pic_url":"https://scontent-ort2-1.cdninstagram.com/v/t51.2885-19/s150x150/92024224_571394950144815_6785941292800016384_n.jpg?_nc_ht=scontent-ort2-1.cdninstagram.com&_nc_ohc=HGoGEHcRIWkAX_awCeB&oh=f7a064eaaa32db99daa9231823d46bb1&oe=5F414938","username":"nana_amakye_korankye"},"likes":0,"comments":0},{"id":"17950223062357599","text":"Spooky","created_at":1595501808,"did_report_as_spam":false,"owner":{"id":"2652537964","is_verified":false,"profile_pic_url":"https://scontent-ort2-1.cdninstagram.com/v/t51.2885-19/s150x150/92024224_571394950144815_6785941292800016384_n.jpg?_nc_ht=scontent-ort2-1.cdninstagram.com&_nc_ohc=HGoGEHcRIWkAX_awCeB&oh=f7a064eaaa32db99daa9231823d46bb1&oe=5F414938","username":"nana_amakye_korankye"},"likes":0,"comments":0}]