[{"id":"17876240929770520","text":"Cool","created_at":1595703614,"did_report_as_spam":false,"owner":{"id":"3300894250","is_verified":false,"profile_pic_url":"https://scontent-ort2-1.cdninstagram.com/v/t51.2885-19/s150x150/60630337_460185108063957_19072626911608832_n.jpg?_nc_ht=scontent-ort2-1.cdninstagram.com&_nc_ohc=CKiP2nURBDEAX9LvD5l&oh=a061dafc0d4bd7ad9c8f5ae1e0152910&oe=5F463CF1","username":"sylvesterosime"},"likes":0,"comments":0},{"id":"18044420518262428","text":"Youngnikram","created_at":1595703630,"did_report_as_spam":false,"owner":{"id":"35694575539","is_verified":false,"profile_pic_url":"https://scontent-ort2-1.cdninstagram.com/v/t51.2885-19/s150x150/107501951_748888222337883_2433442513461870407_n.jpg?_nc_ht=scontent-ort2-1.cdninstagram.com&_nc_ohc=G5AkUMXpPOcAX9VOT5r&oh=d01c088ad968afa679303cf2da821952&oe=5F4567F7","username":"el_finito9"},"likes":0,"comments":0},{"id":"17890926487590374","text":"Cool","created_at":1595703632,"did_report_as_spam":false,"owner":{"id":"3300894250","is_verified":false,"profile_pic_url":"https://scontent-ort2-1.cdninstagram.com/v/t51.2885-19/s150x150/60630337_460185108063957_19072626911608832_n.jpg?_nc_ht=scontent-ort2-1.cdninstagram.com&_nc_ohc=CKiP2nURBDEAX9LvD5l&oh=a061dafc0d4bd7ad9c8f5ae1e0152910&oe=5F463CF1","username":"sylvesterosime"},"likes":0,"comments":0}]