[{"id":"17867064985901557","text":"youngnikgram","created_at":1595699110,"did_report_as_spam":false,"owner":{"id":"2263865072","is_verified":false,"profile_pic_url":"https://scontent-ort2-1.cdninstagram.com/v/t51.2885-19/s150x150/53570332_273138880064870_9034910160396484608_n.jpg?_nc_ht=scontent-ort2-1.cdninstagram.com&_nc_ohc=5RNjIqeOCowAX-lzoTw&oh=86aabd4e5e9e9ccbc644ef0a7b67a55e&oe=5F44801E","username":"joe.kien"},"likes":0,"comments":0},{"id":"17884928788632305","text":"Youngnikgram","created_at":1595699111,"did_report_as_spam":false,"owner":{"id":"39191322433","is_verified":false,"profile_pic_url":"https://scontent-ort2-1.cdninstagram.com/v/t51.2885-19/s150x150/108271492_964176784042501_8422598799764874422_n.jpg?_nc_ht=scontent-ort2-1.cdninstagram.com&_nc_ohc=VTBy9oYyNscAX8Gqjgi&oh=085abba73fd31182f4630c33e926af01&oe=5F454F9D","username":"merilinohephzibah"},"likes":0,"comments":0},{"id":"18070622806219997","text":"youngnikgram","created_at":1595699138,"did_report_as_spam":false,"owner":{"id":"34847084133","is_verified":false,"profile_pic_url":"https://scontent-ort2-1.cdninstagram.com/v/t51.2885-19/s150x150/95337063_260751211745664_591671301672796160_n.jpg?_nc_ht=scontent-ort2-1.cdninstagram.com&_nc_ohc=NKs7FmLwb4kAX8nYdTE&oh=74483bee9e501f1e9f42003d6acdc708&oe=5F45CE29","username":"khalidemm1"},"likes":0,"comments":0},{"id":"18125142004118112","text":"Cool","created_at":1595699138,"did_report_as_spam":false,"owner":{"id":"31321722144","is_verified":false,"profile_pic_url":"https://scontent-ort2-1.cdninstagram.com/v/t51.2885-19/s150x150/88391545_487053695516626_4741821882523713536_n.jpg?_nc_ht=scontent-ort2-1.cdninstagram.com&_nc_ohc=phMcL1E8yk4AX9ClFgm&oh=4873ca1fa9668bbb5e010efd0d75d0a3&oe=5F47AF87","username":"rotimisamolaye1"},"likes":0,"comments":0},{"id":"17844337850310013","text":"Young","created_at":1595699149,"did_report_as_spam":false,"owner":{"id":"35775409568","is_verified":false,"profile_pic_url":"https://scontent-ort2-1.cdninstagram.com/v/t51.2885-19/s150x150/97144403_2749746285255852_5786223762722521088_n.jpg?_nc_ht=scontent-ort2-1.cdninstagram.com&_nc_ohc=y43RVHecF7UAX_oPn7d&oh=40980981ce3e114d14196cf1e95cbcf9&oe=5F4723EA","username":"princely_10"},"likes":0,"comments":0},{"id":"17848149995246303","text":"Youngnigram","created_at":1595699149,"did_report_as_spam":false,"owner":{"id":"2346591133","is_verified":false,"profile_pic_url":"https://scontent-ort2-1.cdninstagram.com/v/t51.2885-19/s150x150/106706151_1569776193182649_2823345389371234961_n.jpg?_nc_ht=scontent-ort2-1.cdninstagram.com&_nc_ohc=agxxJUzQqI4AX90a_lO&oh=4a76f73509123944c43f4a9d581d8801&oe=5F44A613","username":"official_ayodele_king"},"likes":0,"comments":0}]